fusion_surrogates/__init__.py
fusion_surrogates/common/__init__.py
fusion_surrogates/common/networks.py
fusion_surrogates/common/networks_test.py
fusion_surrogates/common/transforms.py
fusion_surrogates/common/transforms_test.py
fusion_surrogates/qlknn/__init__.py
fusion_surrogates/qlknn/qlknn_model.py
fusion_surrogates/qlknn/qlknn_model_test.py
fusion_surrogates/qlknn/qlknn_model_test_utils.py
fusion_surrogates/qlknn/models/README.md
fusion_surrogates/qlknn/models/qlknn_7_11.onnx
fusion_surrogates/qlknn/models/qlknn_7_11.qlknn
fusion_surrogates/qlknn/models/qlknn_7_11_onnx_test.py
fusion_surrogates/qlknn/models/qlknn_7_11_test.py
fusion_surrogates/qlknn/models/qlknn_7_11_test_data.npz
fusion_surrogates/qlknn/models/registry.py
fusion_surrogates/tglfnn_ukaea/README.md
fusion_surrogates/tglfnn_ukaea/__init__.py
fusion_surrogates/tglfnn_ukaea/tglfnn_ukaea_model.py
fusion_surrogates/tglfnn_ukaea/tglfnn_ukaea_model_test.py
fusion_surrogates-0.4.4.dist-info/licenses/LICENSE
fusion_surrogates-0.4.4.dist-info/METADATA
fusion_surrogates-0.4.4.dist-info/WHEEL
fusion_surrogates-0.4.4.dist-info/top_level.txt
fusion_surrogates-0.4.4.dist-info/RECORD
