Metadata-Version: 2.4
Name: fusion_surrogates
Version: 0.4.4
Summary: Transport surrogate models for Tokamak fusion.
Author: DeepMind
License-Expression: Apache-2.0
Classifier: Intended Audience :: Science/Research
Requires-Python: >=3.11
License-File: LICENSE
Requires-Dist: absl-py>=2.0.0
Requires-Dist: flax>=0.7.5
Requires-Dist: immutabledict
Requires-Dist: jax>=0.4.31
Requires-Dist: numpy>2
Requires-Dist: setuptools; python_version >= "3.11"
Provides-Extra: tglfnnukaea
Requires-Dist: tglfnn_ukaea==0.1.0; extra == "tglfnnukaea"
Provides-Extra: testing
Requires-Dist: fusion_surrogates[tglfnnukaea]; extra == "testing"
Requires-Dist: chex; extra == "testing"
Requires-Dist: isort; extra == "testing"
Requires-Dist: jaxonnxruntime; extra == "testing"
Requires-Dist: onnx; extra == "testing"
Requires-Dist: pytest; extra == "testing"
Requires-Dist: pytest-xdist; extra == "testing"
Requires-Dist: pylint>=2.6.0; extra == "testing"
Requires-Dist: pyink; extra == "testing"
Dynamic: license-file
